SimpleLRUCache-0.2.dist-info/DESCRIPTION.rst
SimpleLRUCache-0.2.dist-info/METADATA
SimpleLRUCache-0.2.dist-info/RECORD
SimpleLRUCache-0.2.dist-info/WHEEL
SimpleLRUCache-0.2.dist-info/metadata.json
SimpleLRUCache-0.2.dist-info/top_level.txt
simplelrucache/__init__.py
