Metadata-Version: 2.0
Name: SimpleLRUCache
Version: 0.2
Summary: Simple LRU cache for python. Provides a dictionary-like, forgetful object.
Home-page: https://github.com/JohannesBuchner/SimpleLRUCache
Author: Johannes Buchner, Chris Stucchio
Author-email: buchner.johannes@gmx.at
License: Dual: GPL v3 or BSD
Platform: UNKNOWN
